vnkline/Demo.py
vnkline/__init__.py
vnkline/globaltype.py
vnkline/globalvar.py
vnkline/module_combinekline.py
vnkline/module_config.py
vnkline/module_kline.py
vnkline/vnklineservice.py
vnkline-1.0.0.2.data/data/bitmaps/libcurl.dll
vnkline-1.0.0.2.data/data/bitmaps/libeay32.dll
vnkline-1.0.0.2.data/data/bitmaps/ssleay32.dll
vnkline-1.0.0.2.data/data/bitmaps/vnklineservice.dll
vnkline-1.0.0.2.data/data/bitmaps/vnklineservice.ini
vnkline-1.0.0.2.data/data/bitmaps/zlibwapi.dll
vnkline-1.0.0.2.dist-info/LICENSE.txt
vnkline-1.0.0.2.dist-info/METADATA
vnkline-1.0.0.2.dist-info/WHEEL
vnkline-1.0.0.2.dist-info/top_level.txt
vnkline-1.0.0.2.dist-info/RECORD
