Metadata-Version: 2.1
Name: vnkline
Version: 1.0.0.2
Summary: vnkline
Home-page: https://gitee.com/vnpypro/vnkline
Author: quant lin
Author-email: 1196999641@qq.com
License: https://gitee.com/vnpypro/vnklineservice/blob/master/LICENSE
Keywords: barcode DataMatrix QRCode 1D PDF417
Platform: UNKNOWN
Classifier: Development Status :: 5 - Production/Stable
Classifier: Intended Audience :: Developers
Classifier: Topic :: Software Development :: Libraries
Classifier: License :: Other/Proprietary License
Classifier: Programming Language :: Python :: 3
License-File: LICENSE.txt
Requires-Dist: numpy
Requires-Dist: pandas
Requires-Dist: pyqtgraph
Requires-Dist: PyQt5
